{
    "discord": "Brack Daddy#3493",
    "name": "Brack Daddy",
    "xws": {
        "faction": "galacticempire",
        "name": "Brack Lee JTO",
        "pilots": [
            {
                "id": "countdown",
                "points": 53,
                "ship": "tieskstriker",
                "upgrades": {
                    "device": [
                        "proximitymines"
                    ],
                    "talent": [
                        "swarmtactics"
                    ]
                }
            },
            {
                "id": "redline",
                "points": 70,
                "ship": "tiecapunisher",
                "upgrades": {
                    "device": [
                        "connernets"
                    ],
                    "missile": [
                        "ionmissiles"
                    ],
                    "modification": [
                        "tacticalscrambler"
                    ],
                    "torpedo": [
                        "advprotontorpedoes"
                    ]
                }
            },
            {
                "id": "sigmasquadronace",
                "points": 72,
                "ship": "tiephphantom",
                "upgrades": {
                    "gunner": [
                        "fifthbrother"
                    ],
                    "modification": [
                        "stealthdevice"
                    ],
                    "sensor": [
                        "firecontrolsystem"
                    ],
                    "talent": [
                        "lonewolf"
                    ]
                }
            }
        ],
        "points": 195,
        "vendor": {},
        "version": "2.0.0"
    },
    "yasb": "https://raithos.github.io/?f=Galactic%20Empire&d=v8ZsZ200Z209X132WW70WY191XW134W101WWW68WW110Y201X124W113W82W166&sn=Brack%20Lee%20JTO&obs="
}