{
    "discord": "Herschet#3836",
    "name": "Herschet",
    "xws": {
        "faction": "rebelalliance",
        "name": "Random Squad",
        "pilots": [
            {
                "id": "knavesquadronescort",
                "points": 59,
                "ship": "ewing",
                "upgrades": {
                    "torpedo": [
                        "plasmatorpedoes"
                    ]
                }
            },
            {
                "id": "dutchvander",
                "points": 66,
                "ship": "btla4ywing",
                "upgrades": {
                    "device": [
                        "connernets"
                    ],
                    "modification": [
                        "hullupgrade"
                    ],
                    "talent": [
                        "crackshot"
                    ],
                    "torpedo": [
                        "protontorpedoes"
                    ],
                    "turret": [
                        "dorsalturret"
                    ]
                }
            },
            {
                "id": "airencracken",
                "points": 49,
                "ship": "z95af4headhunter",
                "upgrades": {
                    "missile": [
                        "protonrockets"
                    ],
                    "modification": [
                        "stealthdevice"
                    ]
                }
            },
            {
                "id": "zeborrelios-tielnfighter",
                "points": 24,
                "ship": "tielnfighter",
                "upgrades": {}
            }
        ],
        "points": 198,
        "vendor": {},
        "version": "2.0.0"
    },
    "yasb": "https://raithos.github.io/?f=Rebel%20Alliance&d=v8ZsZ200Z24XW234WWY27X116W137W136WW164W68WY54XW102W166Y15X&sn=Random%20Squad&obs="
}