{
    "name": "Ben",
    "number": 1,
    "xws": {
        "faction": "galacticempire",
        "name": "Random Squad",
        "pilots": [
            {
                "id": "planetarysentinel",
                "points": 42,
                "ship": "tieskstriker",
                "upgrades": {
                    "device": [
                        "protonbombs"
                    ],
                    "modification": [
                        "stealthdevice"
                    ]
                }
            },
            {
                "id": "rhosquadronpilot",
                "points": 50,
                "ship": "alphaclassstarwing",
                "upgrades": {
                    "sensor": [
                        "trajectorysimulator"
                    ],
                    "torpedo": [
                        "plasmatorpedoes"
                    ]
                }
            },
            {
                "id": "stormsquadronace",
                "points": 47,
                "ship": "tieadvancedx1",
                "upgrades": {
                    "missile": [
                        "clustermissiles"
                    ],
                    "sensor": [
                        "passivesensors"
                    ]
                }
            },
            {
                "id": "coloneljendon",
                "points": 60,
                "ship": "lambdaclasst4ashuttle",
                "upgrades": {
                    "cannon": [
                        "autoblasters"
                    ],
                    "crew": [
                        "isbslicer"
                    ],
                    "modification": [
                        "electronicbaffle"
                    ],
                    "title": [
                        "st321"
                    ]
                }
            }
        ],
        "points": 199,
        "vendor": {},
        "version": "2.0.0"
    },
    "yasb": "https://raithos.github.io/?f=Galactic%20Empire&d=v8ZsZ200Z213XW69W166Y163XW114W234WWWY177XW240W98WY167XW232WW38W106W162&sn=Random%20Squad&obs="
}