{
    "name": "CatherineNyxsera",
    "number": 2,
    "xws": {
        "faction": "separatistalliance",
        "name": "Random Squad",
        "pilots": [
            {
                "id": "066",
                "points": 97,
                "ship": "sithinfiltrator",
                "upgrades": {
                    "cannon": [
                        "tractorbeam"
                    ],
                    "crew": [
                        "chancellorpalpatine",
                        "gnkgonkdroid"
                    ],
                    "device": [
                        "connernets"
                    ],
                    "modification": [
                        "ablativeplating"
                    ],
                    "talent": [
                        "crackshot"
                    ],
                    "torpedo": [
                        "iontorpedoes"
                    ]
                }
            },
            {
                "id": "tradefederationdrone",
                "points": 21,
                "ship": "vultureclassdroidfighter",
                "upgrades": {
                    "modification": [
                        "electronicbaffle"
                    ]
                }
            },
            {
                "id": "separatistdrone",
                "points": 32,
                "ship": "vultureclassdroidfighter",
                "upgrades": {
                    "configuration": [
                        "grapplingstruts"
                    ],
                    "missile": [
                        "protonrockets"
                    ],
                    "modification": [
                        "targetingcomputer"
                    ]
                }
            },
            {
                "id": "generalgrievous",
                "points": 49,
                "ship": "belbullab22starfighter",
                "upgrades": {
                    "modification": [
                        "hullupgrade"
                    ]
                }
            }
        ],
        "points": 199,
        "vendor": {},
        "version": "2.0.0"
    },
    "yasb": "https://raithos.github.io/?f=Separatist%20Alliance&d=v8ZsZ200Z335X116W13W135W217W32W68W103WWY279XWW106Y343X102W208W249Y305XWW164W&sn=Random%20Squad&obs="
}