{
    "name": "Josh",
    "number": 1,
    "xws": {
        "faction": "galacticrepublic",
        "name": "Random Squad",
        "pilots": [
            {
                "id": "oddball-btlbywing",
                "points": 67,
                "ship": "btlbywing",
                "upgrades": {
                    "device": [
                        "protonbombs"
                    ],
                    "modification": [
                        "targetingcomputer"
                    ],
                    "talent": [
                        "elusive"
                    ],
                    "torpedo": [
                        "plasmatorpedoes"
                    ],
                    "turret": [
                        "dorsalturret"
                    ]
                }
            },
            {
                "id": "dineeellberger",
                "points": 47,
                "ship": "nabooroyaln1starfighter",
                "upgrades": {
                    "talent": [
                        "swarmtactics"
                    ],
                    "torpedo": [
                        "iontorpedoes"
                    ]
                }
            },
            {
                "id": "104thbattalionpilot",
                "points": 49,
                "ship": "arc170starfighter",
                "upgrades": {
                    "astromech": [
                        "r2astromech"
                    ],
                    "gunner": [
                        "skilledbombardier"
                    ]
                }
            },
            {
                "id": "bravoflightofficer",
                "points": 33,
                "ship": "nabooroyaln1starfighter",
                "upgrades": {}
            }
        ],
        "points": 196,
        "vendor": {},
        "version": "2.0.0"
    },
    "yasb": "https://raithos.github.io/?f=Galactic%20Republic&d=v8ZsZ200Z366X119W137W234WWW69W249Y331X132WWW135Y341XWW88W2WY323XWW&sn=Random%20Squad&obs="
}