{"faction":"resistance","pilots":[{"id":"nodinchavdri","ship":"resistancetransport","points":63,"upgrades":{"cannon":["tractorbeam"],"torpedo":["advprotontorpedoes"],"crew":["novicetechnician","perceptivecopilot"],"astromech":["r5x3"],"modification":["delayedfuses"]}},{"id":"resistancesympathizer","ship":"scavengedyt1300","points":81,"upgrades":{"crew":["amilynholdo","freelanceslicer"],"illicit":["inertialdampeners"],"modification":["ablativeplating"],"title":["reysmillenniumfalcon"]}},{"id":"lulolampar","ship":"rz2awing","points":53,"upgrades":{"talent":["swarmtactics"],"tech":["ferrospherepaint"]}}],"points":197,"vendor":{},"version":"2.0.0","name":"Random Squad"}