{
    "name": "Ryan Costello",
    "number": 2,
    "xws": {
        "faction": "firstorder",
        "name": "Random Squad",
        "pilots": [
            {
                "id": "commandermalarus",
                "points": 38,
                "ship": "tiefofighter",
                "upgrades": {}
            },
            {
                "id": "avenger",
                "points": 56,
                "ship": "tievnsilencer",
                "upgrades": {}
            },
            {
                "id": "rush",
                "points": 58,
                "ship": "tievnsilencer",
                "upgrades": {
                    "tech": [
                        "biohexacryptcodes"
                    ]
                }
            },
            {
                "id": "firstorderprovocateur",
                "points": 45,
                "ship": "tiebainterceptor",
                "upgrades": {}
            }
        ],
        "points": 197,
        "vendor": {},
        "version": "2.0.0"
    },
    "yasb": "https://raithos.github.io/?f=First%20Order&d=v8ZsZ200Z266XWWY283XWWWY386X202WWY384XWWW&sn=Random%20Squad&obs="
}