{
    "name": "Spinner",
    "number": 1,
    "xws": {
        "faction": "rebelalliance",
        "name": "Random Squad",
        "pilots": [
            {
                "id": "lieutenantblount",
                "points": 40,
                "ship": "z95af4headhunter",
                "upgrades": {
                    "missile": [
                        "protonrockets"
                    ],
                    "talent": [
                        "intimidation"
                    ]
                }
            },
            {
                "id": "corranhorn",
                "points": 75,
                "ship": "ewing",
                "upgrades": {
                    "astromech": [
                        "r2astromech"
                    ]
                }
            },
            {
                "id": "benthictwotubes",
                "points": 46,
                "ship": "ut60duwing",
                "upgrades": {
                    "configuration": [
                        "pivotwing"
                    ]
                }
            },
            {
                "id": "airencracken",
                "points": 36,
                "ship": "z95af4headhunter",
                "upgrades": {}
            }
        ],
        "points": 197,
        "vendor": {},
        "version": "2.0.0"
    },
    "yasb": "https://raithos.github.io/?f=Rebel%20Alliance&d=v8ZsZ200Z55X122W102WY21XWWW2WY36XWWWWW140Y54XWW&sn=Random%20Squad&obs="
}