{"faction":"rebelalliance","pilots":[{"id":"leebo","ship":"yt2400lightfreighter","points":88,"upgrades":{"missile":["clustermissiles"],"illicit":["deadmansswitch"]}},{"id":"jakefarrell","ship":"rz1awing","points":45,"upgrades":{"talent":["juke","daredevil"]}},{"id":"wardensquadronpilot","ship":"btls8kwing","points":66,"upgrades":{"torpedo":["protontorpedoes"],"missile":["diamondboronmissiles"],"device":["ionbombs"],"modification":["advancedslam"]}}],"points":199,"vendor":{},"version":"2.0.0","name":"Random Squad"}