{
    "name": "TonyC (Extended)",
    "number": 1,
    "xws": {
        "faction": "galacticempire",
        "name": "Random Squad",
        "pilots": [
            {
                "id": "onyxsquadronace",
                "points": 80,
                "ship": "tieddefender",
                "upgrades": {
                    "missile": [
                        "clustermissiles"
                    ],
                    "talent": [
                        "marksmanship"
                    ]
                }
            },
            {
                "id": "tomaxbren",
                "points": 65,
                "ship": "tiesabomber",
                "upgrades": {
                    "device": [
                        "bombletgenerator"
                    ],
                    "missile": [
                        "diamondboronmissiles"
                    ],
                    "modification": [
                        "afterburners"
                    ],
                    "torpedo": [
                        "protontorpedoes"
                    ]
                }
            },
            {
                "id": "vedfoslo",
                "points": 53,
                "ship": "tieadvancedx1",
                "upgrades": {
                    "missile": [
                        "homingmissiles"
                    ],
                    "modification": [
                        "targetingcomputer"
                    ],
                    "talent": [
                        "marksmanship"
                    ]
                }
            }
        ],
        "points": 198,
        "vendor": {},
        "version": "2.0.0"
    },
    "yasb": "https://raithos.github.io/?f=Galactic%20Empire&d=v8ZsZ200Z197X125WWW98Y205XW136W238WWW67WW105Y175X125WW100W249&sn=Random%20Squad&obs="
}